collective.fullcalendar-1.6-py3.11-nspkg.pth
collective/fullcalendar/__init__.py
collective/fullcalendar/configure.zcml
collective/fullcalendar/interfaces.py
collective/fullcalendar/permissions.zcml
collective/fullcalendar/setuphandlers.py
collective/fullcalendar/testing.py
collective/fullcalendar/browser/__init__.py
collective/fullcalendar/browser/configure.zcml
collective/fullcalendar/browser/fullcalendar.py
collective/fullcalendar/browser/overrides/.gitkeep
collective/fullcalendar/browser/static/.gitkeep
collective/fullcalendar/browser/static/js/locales-all.min.js
collective/fullcalendar/browser/static/js/main.min.js
collective/fullcalendar/locales/README.rst
collective/fullcalendar/locales/__init__.py
collective/fullcalendar/locales/collective.fullcalendar.pot
collective/fullcalendar/locales/update.py
collective/fullcalendar/locales/update.sh
collective/fullcalendar/locales/de/LC_MESSAGES/collective.fullcalendar.po
collective/fullcalendar/locales/en/LC_MESSAGES/collective.fullcalendar.po
collective/fullcalendar/locales/no/LC_MESSAGES/collective.fullcalendar.po
collective/fullcalendar/profiles/default/actions.xml
collective/fullcalendar/profiles/default/browserlayer.xml
collective/fullcalendar/profiles/default/catalog.xml
collective/fullcalendar/profiles/default/metadata.xml
collective/fullcalendar/profiles/default/registry.xml
collective/fullcalendar/profiles/default/rolemap.xml
collective/fullcalendar/profiles/default/types/Collection.xml
collective/fullcalendar/profiles/default/types/Folder.xml
collective/fullcalendar/profiles/uninstall/actions.xml
collective/fullcalendar/profiles/uninstall/browserlayer.xml
collective/fullcalendar/profiles/uninstall/registry.xml
collective/fullcalendar/tests/__init__.py
collective/fullcalendar/tests/test_robot.py
collective/fullcalendar/tests/test_setup.py
collective/fullcalendar/tests/test_upgrade_step_1001.py
collective/fullcalendar/tests/test_view_edit_event.py
collective/fullcalendar/tests/test_view_fullcalendar_view.py
collective.fullcalendar-1.6.dist-info/LICENSE.GPL
collective.fullcalendar-1.6.dist-info/LICENSE.rst
collective.fullcalendar-1.6.dist-info/METADATA
collective.fullcalendar-1.6.dist-info/WHEEL
collective.fullcalendar-1.6.dist-info/entry_points.txt
collective.fullcalendar-1.6.dist-info/namespace_packages.txt
collective.fullcalendar-1.6.dist-info/top_level.txt
collective.fullcalendar-1.6.dist-info/RECORD
