Metadata-Version: 2.1
Name: collective.fullcalendar
Version: 1.6
Summary: Fullcalendar for Plone
Home-page: https://github.com/collective/collective.fullcalendar
Author: Werkbank GmbH
Author-email: mail@werkbank.de
License: GPL version 2
Project-URL: PyPI, https://pypi.python.org/pypi/collective.fullcalendar
Project-URL: Source, https://github.com/collective/collective.fullcalendar
Project-URL: Tracker, https://github.com/collective/collective.fullcalendar/issues
Keywords: Python Plone CMS
Classifier: Environment :: Web Environment
Classifier: Framework :: Plone
Classifier: Framework :: Plone :: Addon
Classifier: Framework :: Plone :: 5.2
Classifier: Framework :: Plone :: 6.0
Classifier: Programming Language :: Python
Classifier: Programming Language :: Python :: 2.7
Classifier: Programming Language :: Python :: 3.6
Classifier: Programming Language :: Python :: 3.7
Classifier: Programming Language :: Python :: 3.8
Classifier: Programming Language :: Python :: 3.9
Classifier: Operating System :: OS Independent
Classifier: License :: OSI Approved :: GNU General Public License v2 (GPLv2)
License-File: LICENSE.GPL
License-File: LICENSE.rst
Requires-Dist: setuptools
Requires-Dist: z3c.jbot
Requires-Dist: plone.api >=1.8.4
Requires-Dist: plone.restapi
Requires-Dist: plone.app.dexterity
Provides-Extra: test
Requires-Dist: plone.app.testing ; extra == 'test'
Requires-Dist: plone.testing >=5.0.0 ; extra == 'test'
Requires-Dist: plone.app.contenttypes ; extra == 'test'
Requires-Dist: plone.app.robotframework[debug] ; extra == 'test'
